LICENSE
README.md
setup.py
clspotify.egg-info/PKG-INFO
clspotify.egg-info/SOURCES.txt
clspotify.egg-info/dependency_links.txt
clspotify.egg-info/requires.txt
clspotify.egg-info/top_level.txt
zspotify/__main__.py
zspotify/album.py
zspotify/app.py
zspotify/config.py
zspotify/const.py
zspotify/loader.py
zspotify/playlist.py
zspotify/podcast.py
zspotify/termoutput.py
zspotify/track.py
zspotify/utils.py
zspotify/zspotify.py