Metadata-Version: 2.1
Name: clspotify
Version: 0.5.3.1
Summary: A spotify downloader.
Home-page: https://github.com/agent255/clspotify.git
Author: hr
Author-email: hemagna.rao@gmail.com
License: GPLv3
Platform: UNKNOWN
Classifier: License :: OSI Approved :: GNU General Public License v3 (GPLv3)
Classifier: Programming Language :: Python :: 3.9
License-File: LICENSE
